{"hash":"878a597844db8e690a30b7fec33be346d7d73955","data":null,"context":{"id":"e05df9b1-985c-4c6e-8083-83f405213369","name":"D.Bar Restaurant","branch":"Gastronomie","phone":"0201 84 07 89 26","email":"os@dbar-essen.de","website":"http://www.dbar-essen.de","address":"Kahrstr. 80","image":"","postal":45128,"town":"Essen","keywords":"Bewirtung, Gaststätte, Gemütliche Atmosphäre","brands":"","greview_1_rating":1,"greview_1_zeit":"vor 2 Jahren","greview_1_text":"","greview_1_reviewer":"Bernd Jung","greview_1_localguide":1,"greview_1_beantwortet":""}}