{"hash":"65e2bbd09f8cf90eca8adbf53c9f9312bd816ae9","data":null,"context":{"id":"9e3e5406-dfad-4e46-8872-fbeaf33a41a2","name":"Restaurant International","branch":"Gastronomie","phone":"0208 20 82 35","email":"kontakt@international-restaurant.de","website":"http://www.international-restaurant.de","address":"Helmholtzstr. 108","image":"","postal":46045,"town":"Oberhausen","keywords":"Beilage, Fischspezialität, Gerichte, Steak, internationale Küchen, kroatische Küchen, Gemütliche Atmosphäre","brands":"","greview_1_rating":1,"greview_1_zeit":"vor 5 Monaten","greview_1_text":"Wir haben noch nie so schlecht gegessen.  Das Restaurant war sehr gut besucht Kellner sehr nett, aber das Essen war grauenvoll. Ich hatte ein Schweinefilet mit Bratkartoffeln Gemüse und Sauce Hollandaise. Eins von den drei Stücken Fleisch war schlecht Bratkartoffeln verbrannt und Gemüse verkocht.  Das Essen von meinem Mann war auch nicht viel besser.","greview_1_reviewer":"Nicole Bujok","greview_1_localguide":0,"greview_1_beantwortet":"Hallo Frau Bujok,leider können wir Ihre Unzufriedenheit nicht nachvollziehen.Speziell Ihr Einleitungssatz lässt an Fingerspitzengefühl zu wünschen übrig. Solche Aussagen sollte man sich gut überlegen, da diese sich geschäftsschädigend auswirken können.Ihre Unzufriedenheit hätten Sie auch einfach vor Ort äußern können. Das hätte es uns allen um einiges einfacher gemacht.Uns wundert nur, dass Sie diese Kritik zu einem unserer meistverkauften Gerichte äußern. Wie kann denn bei 3 Schweinefiletmedaillons eins schlecht sein und 2 gut? Also entweder sind alle gut oder alle schlecht! Das es Ihrem Mann natürlich auch nicht so geschmackt hat, war bei Ihrer offensichtlichen Unzufriedenheit zu erwarten.Wie Sie aber selbst vor Ort sehen konnten, schmeckt es der Mehrheit unserer Gäste gut bei uns.Wir danken Ihnen nichtsdestotrotz für Ihren Besuch und hoffen das Sie in anderen Lokalen zufriedener werden.Mit freundlichen Grüßen"}}