{"hash":"878a597844db8e690a30b7fec33be346d7d73955","data":null,"context":{"id":"ddfd7eea-1fa7-422e-890d-9ed52b6a5fda","name":"Daylis Restaurant und Conference Gaststätte","branch":"Gastronomie","phone":"02173 39 96-2 01","email":"daylis@sv-group.de","website":"http://www.daylis.de","address":"Elisabeth-Selbert-Str. 4A","image":"","postal":40764,"town":"Langenfeld (Rheinland)","keywords":"","brands":"","greview_1_rating":"","greview_1_zeit":"","greview_1_text":"","greview_1_reviewer":"","greview_1_localguide":"","greview_1_beantwortet":""}}