{"hash":"65e2bbd09f8cf90eca8adbf53c9f9312bd816ae9","data":null,"context":{"id":"108ff556-d38e-4592-98e2-a78e8f6bb603","name":"Bastkowski Paul","branch":"Tischlereien","phone":"02166 2 24 61","email":"info@schreinerei-bastkowski.de","website":"https://www.schreinerei-bastkowski.de","address":"Sonnenstr. 4","image":"","postal":41238,"town":"Mönchengladbach","keywords":"Innenausbau, Möbelschreiner, Reparaturen aller Art, Schreinerei, Schreinermeister, Tischlereien, Schreiner","brands":"","greview_1_rating":5,"greview_1_zeit":"vor 4 Monaten","greview_1_text":"Sehr prezise Arbeit und faire Preise. Nur weiter zu empfehlen.","greview_1_reviewer":"Joline Gingter","greview_1_localguide":0,"greview_1_beantwortet":""}}