{"hash":"65e2bbd09f8cf90eca8adbf53c9f9312bd816ae9","data":null,"context":{"id":"7344f2bd-4669-40c2-868f-569a5e2779e2","name":"Terbeek Bedachung GmbH","branch":"Dachdeckereien","phone":"02152 9 19 90","email":"terbeek-bedachungen@t-online.de","website":"http://www.bedachungen-terbeek.de","address":"Am Selder 49A","image":"http://cdn.localdash.io/uscan_img/800_gmb.jpeg?key=83439b8","postal":47906,"town":"Kempen","keywords":"Schiefer, Abdichtungstechnik, Dachsanierung, Dachgauben, Dachdeckermeister, Flachdach, Dachbegr체nungen, Dachabdichtungen, Dachfenster, Dachgaube, Holzbau, Bauklempnerei, Bedachungen, Dachbegr체nung, Winterg채rten, Balkonsanierungen, Fassadenbekleidungen, Klempnermeisterbetrieb, Dachdeckermeisterbetrieb, Dacharbeiten, Dachdeckerei, Bedachungen aller Art, Dachdecker, Dachdeckmeisterbetrieb, Fassaden, Meisterbetrieb, Klempnermeister, Dachfenstereinbau, Dachrinnenreinigung, Dachd채mmungen, Dachisolierungen","brands":"","greview_1_rating":5,"greview_1_zeit":"vor 5 Monaten","greview_1_text":"Gute Beratung und nettes Team. Voll zufrieden","greview_1_reviewer":"Markus Larmann","greview_1_localguide":0,"greview_1_beantwortet":""}}