{"hash":"878a597844db8e690a30b7fec33be346d7d73955","data":null,"context":{"id":"7da6975f-2d55-4cf1-99a3-443e4c4b973f","name":"HANS IM GLÜCK Burgergrill & Bar","branch":"Gastronomie","phone":"0221 29 89 21 63","email":"amring@hansimglueck-burgergrill.de","website":"https://hansimglueck-burgergrill.de/standort/koeln-am-ring/?utm_source=extnet&utm_medium=yext&utm_campaign=3","address":"Hohenzollernring 38-40","image":"","postal":50672,"town":"Köln","keywords":"","brands":"","greview_1_rating":1,"greview_1_zeit":"vor 2 Monaten","greview_1_text":"1 Stern für die Bedienung.Das Restaurant ist sehr eng und dunkel!Wegen Corona soll man auch wenn man draußen an der stark befahrenen Straße sitzen soll, seine ganzen Daten preis geben. Name, Adresse, Handy&Telefonnummer..Da geht man lieber paar Meter weiter zur Pommesbude. Keine Datensammlung und man bekommt trotzdem seine Pommes für um draußen zu sitzen.","greview_1_reviewer":"Li li","greview_1_localguide":0,"greview_1_beantwortet":"Hallo Li! Es ist schade zu hören, dass Du Deinen Besuch nicht genießen konntest. Da uns daran gelegen ist uns zu verbessern, würden wir uns freuen, wenn Du uns eine kurze Rückmeldung geben könntest, warum Du mit unserem Service nicht zufrieden warst. Bitte schreibe uns eine Nachricht an https://hansimglueck-burgergrill.de/lob-und-tadel/. Somit können wir das entsprechend intern weitergeben und optimieren. Bezüglich der Personenangaben halten wir uns selbstverständlich an die vorgegebenen Richtlinien und hoffen, Du hast Verständnis dafür. Vielen Dank, Dein HANS IM GLÜCK"}}