{"hash":"878a597844db8e690a30b7fec33be346d7d73955","data":null,"context":{"id":"4bd2c44d-c584-416e-8815-3cf5df7ecdb7","name":"Burger Brothers Essen","branch":"Gastronomie >  Amerikanisch > Gastronomie","phone":"0201 46 68 56 40","email":"essen@burgerbrothers.net","website":"","address":"Friedrich-Ebert-Str. 12","image":"","postal":45127,"town":"Essen","keywords":"Burger","brands":"","greview_1_rating":1,"greview_1_zeit":"vor einem Monat","greview_1_text":"Essen war nicht würzig genug.","greview_1_reviewer":"German Player","greview_1_localguide":0,"greview_1_beantwortet":"Das muss wohl ein Missverständnis sein. Aufgrund von Renovierungsarbeiten haben wir seid dem 24.04.2020 geschlossen. Sie verwechseln uns wohl."}}