{"hash":"65e2bbd09f8cf90eca8adbf53c9f9312bd816ae9","data":null,"context":{"id":"685b4bd6-37c3-4855-86d7-b65cec95e7ef","name":"Restaurant Sengelmannshof","branch":"Gastronomie","phone":"02054 95 97-0","email":"info@sengelmannshof.de","website":"http://www.sengelmannshof.de","address":"Sengelmannsweg 35","image":"","postal":45219,"town":"Essen","keywords":"Biergarten, Catering, Doppelzimmer, Einzelzimmer, Festlichkeiten, Gulaschkanone, Hochzeitszimmer, Hotel, Kegelbahn, Konferenzen, Messe, Messehotel, Partyservice, Restaurant, Rübenkeller, Tagungen, Veranstaltungen, Hochzeit, Hochzeitsfeier, Gästezimmer, Unterkünfte, Unterkunft, Übernachtung, Hochzeiten, Familienfeiern, Geburtstagsfeier, Zimmer, Feier, Party","brands":"","greview_1_rating":"","greview_1_zeit":"","greview_1_text":"","greview_1_reviewer":"","greview_1_localguide":"","greview_1_beantwortet":""}}