{"hash":"65e2bbd09f8cf90eca8adbf53c9f9312bd816ae9","data":null,"context":{"id":"1ec50c1a-eef0-4559-af0b-c8950eef7bce","name":"Pflege- und Betreuungsdienst Böhme","branch":"Pflegedienste","phone":"0211 15 20 06 78","email":"info@pflegedienst-boehme.de","website":"http://www.pflegedienst-böhme.de","address":"Werstener Dorfstr. 86","image":"","postal":40591,"town":"Düsseldorf","keywords":"Karin Kokot-Mönch, Krankenpflege, Wundversorgung, Altenpflege, Ambulanter Pflegedienst, Mobile Pflege, Grundpflege, Behandlungspflege, Verhinderungspflege, Urlaubspflege","brands":"","greview_1_rating":"","greview_1_zeit":"","greview_1_text":"","greview_1_reviewer":"","greview_1_localguide":"","greview_1_beantwortet":""}}