{"hash":"65e2bbd09f8cf90eca8adbf53c9f9312bd816ae9","data":null,"context":{"id":"c6c19ace-2076-44e9-8e4a-1598a0cd1033","name":"Reissdorf En D'r Post Gaststätte  Preuße Markus","branch":"Gastronomie","phone":"02181 4 95 40 75","email":"info@reissdorf-en-dr-post.de","website":"http://www.reissdorf-en-dr-post.de","address":"Friedensstr. 13","image":"","postal":41517,"town":"Grevenbroich","keywords":"","brands":"","greview_1_rating":1,"greview_1_zeit":"vor 11 Monaten","greview_1_text":"In den letzten Jahren habe ich das Reissdorf kennen und lieben gelernt. Leider wurde ich heute eines besseren belehrt und die mahnenden Worte meines Vaters von vor zwei Monaten Gewissheit. Das Reissdorf ist nicht mehr was es war. Nicht sauberes Besteck eingedeckt, Getränke die nicht da waren oder nach ein paar Gläsern ausgingen, das Personal im Service wirkte heute etwas überfordert. Die Speisen, abgesehen vom Nachtisch, waren ok, aber eben auch nur ok. Der Nachtisch stach positiv heraus. Bleibt mir nur die Hoffnung, dass es heute einfach nur ein schlechter Tag war und mein Vater nicht recht hat mit seiner Aussage. Dennoch, das war heute nix, deswegen heute nur 1 Stern.","greview_1_reviewer":"Stephan Arand","greview_1_localguide":1,"greview_1_beantwortet":""}}