{"hash":"65e2bbd09f8cf90eca8adbf53c9f9312bd816ae9","data":null,"context":{"id":"7e91396d-264f-44b8-bb84-4b7f7bb7aedb","name":"Zago Miriam Dr.med. Dermatologie Allergologie","branch":"Medizin >  Haut- und Geschlechtskrankheiten","phone":"02131 6 93 95","email":"dr.zago@t-online.de","website":"http://www.hautarzt-kaarst.de","address":"Alte Heerstr. 18","image":"","postal":41564,"town":"Kaarst","keywords":"","brands":"","greview_1_rating":1,"greview_1_zeit":"vor 5 Tagen","greview_1_text":"Die guten Bewertungen kann ich nicht verstehen. Die Ärztin hat sich keine Zeit genommen. Sie sagte ich soll schnell sagen weil Sie noch andere Patienten hat. Keine 5 min. war ich schon wieder draußen. SOWAS NOCH NIE ERLEBT","greview_1_reviewer":"Khaqan rana","greview_1_localguide":0,"greview_1_beantwortet":"Ein/e Patient/in mit diesem Namen ist in der Praxis nicht bekannt. Ja, ich erlaube mir nach ca. 20 min. Beratung (Zeittracking im Computer) und keiner medizinischen Notwendigkeit den Termin auszudehnen (also rein kosmetischer Beratung, die der Patient ohnehin privat bezahlen müsste) Patienten darauf hinzuweisen, dass wir für weiteres einen neuen Termin vereinbaren müssen."}}