{"hash":"65e2bbd09f8cf90eca8adbf53c9f9312bd816ae9","data":null,"context":{"id":"725c00ac-043b-4693-b721-024a1ece10e0","name":"Gaststätte U76","branch":"Gastronomie","phone":"02151 9 34 16 51","email":"u76-krefeld@gmx.de","website":"https://u-76-restaurant.metro.bar/?lang=de","address":"Hees 84","image":"","postal":47807,"town":"Krefeld","keywords":"","brands":"","greview_1_rating":"","greview_1_zeit":"","greview_1_text":"","greview_1_reviewer":"","greview_1_localguide":"","greview_1_beantwortet":""}}