{"hash":"878a597844db8e690a30b7fec33be346d7d73955","data":null,"context":{"id":"57510ec4-7281-4ab1-ad36-96ba7e95cacc","name":"Salina Restaurant","branch":"Gastronomie >  Spanisch > Gastronomie","phone":"0201 23 89 62","email":"kontakt@salina-essen.de,Kontakt@salina-essen.de","website":"http://www.salina-essen.de","address":"Rellinghauser Str. 423","image":"","postal":45134,"town":"Essen","keywords":"Spanische K체che, Gastst채tte, Gem체tliche Atmosph채re","brands":"","greview_1_rating":1,"greview_1_zeit":"vor einem Monat","greview_1_text":"Schmeckt nicht","greview_1_reviewer":"ayoub Casaoui","greview_1_localguide":0,"greview_1_beantwortet":""}}