{"hash":"878a597844db8e690a30b7fec33be346d7d73955","data":null,"context":{"id":"549b43c5-2201-4a43-837f-40ff5ae15855","name":"Dachdecker-Meisterbetrieb & Holzbau Rack GmbH","branch":"Dachdeckereien","phone":"0208 62 03 06 78","email":"willirack@gmx.de","website":"https://www.dachdeckermeister-oberhausen.de/","address":"Lothringer Str. 167","image":"http://cdn.localdash.io/uscan_img/773_gmb.jpeg?key=83439b8","postal":46045,"town":"Oberhausen","keywords":"Dachtechnik","brands":"","greview_1_rating":1,"greview_1_zeit":"vor 2 Monaten","greview_1_text":"Hat sich nicht gemeldet... Nichts funktioniert. Vergessen...","greview_1_reviewer":"Axel Gebauer","greview_1_localguide":1,"greview_1_beantwortet":""}}