{"hash":"878a597844db8e690a30b7fec33be346d7d73955","data":null,"context":{"id":"2914fa44-d5d8-4416-b92e-f65864f5c9a2","name":"Shanghai Chinesisches Restaurant","branch":"Gastronomie >  Chinesisch","phone":"0211 28 39 19","email":"hejun03@hotmail.com","website":"http://www.chinarestaurant-shanghai-duesseldorf.de","address":"Unter den Eichen 2","image":"","postal":40625,"town":"Düsseldorf","keywords":"Grill, Früchte, Nudelgerichte, Vorspeisen, Garnele, Eis, Meeresfrüchte, Pizza, Nudeln, Olivenöl, Möhren, Salat, Gewürz, Hühnerfleisch, Menükarte, Suppen, Restaurant, Champignons, China-Restaurant, Garnelen, Lieferservice, Topf, Bringdienst, Lieferdienste","brands":"","greview_1_rating":1,"greview_1_zeit":"vor 9 Monaten","greview_1_text":"Nicht zu empfehlen ! Eine Stunde und 25Min auf zwei Mal Nudel mit Hähnchenfleisch,plus der Laden ist gerade Mal 10Min zu Fuß zu erreichen. Wir kriegen kein Anruf,kein nichts wo bescheid gesagt wird es Sache ist. Wir haben drei Mal angerufen,um herauszufinden was Sache ist ? Am Ende wird gesagt unsere Adresse wurde nicht gefunden ? Ehm,keine 10Min zu Fuß,super zentral und dann sowas ? Unverschämt ! Nicht zu empfehlen !","greview_1_reviewer":"Silvije Sulejmani","greview_1_localguide":0,"greview_1_beantwortet":""}}