{"hash":"878a597844db8e690a30b7fec33be346d7d73955","data":null,"context":{"id":"897128ed-da6d-4452-97a5-98fe05484949","name":"Bento Box","branch":"Gastronomie >  Sushispezialitäten","phone":"0221 60 60 17 17","email":"info@bentobox.de,service@bentobox.de","website":"http://www.bentobox.de","address":"Aachener Str. 500","image":"","postal":50933,"town":"Köln","keywords":"","brands":"","greview_1_rating":1,"greview_1_zeit":"vor 3 Monaten","greview_1_text":"Eigentlich sollte ich 0 Sterne geben. Unmöglich, wie die Seite aufgebaut ist, sodass man zu \"falsche Bestellungen\" gezwungen ist!! 2 Spieße und ein paar frittierte was weiß ich was für 9.10€???? Und was soll die halbe Nigiri sein??Unmöglich!!","greview_1_reviewer":"Claudia Hornos der","greview_1_localguide":0,"greview_1_beantwortet":"Hallo Claudia Hornos, es tut mir Leid, dass Sie bei Ihrer letzten Bestellung so schlechte Erfahrungen gemacht haben. Für zukünftige Bestellungen empfehle ich Ihnen, nicht über Online-Lieferportale sondern direkt über unseren eigenen Webshop auf https://shop.bentobox.de/storedata/listStore zu bestellen. Darüber hinaus freuen wir uns, wenn Sie uns bei Problemen oder Fragen in Zukunft direkt kontaktieren, z. B. per E-Mail an: service@bentobox.de. Vielen Dank und freundliche Grüße vom Team der Bento Box"}}