{"hash":"65e2bbd09f8cf90eca8adbf53c9f9312bd816ae9","data":null,"context":{"id":"7370d1b5-94a4-4731-a986-fffe165530eb","name":"Kraemer GmbH & Co. KG","branch":"Dachdeckereien","phone":"02151 59 28 33","email":"buero@bedachungen-kraemer.de","website":"http://www.bedachungen-kraemer.de","address":"Ennsstr. 11","image":"http://cdn.localdash.io/uscan_img/831_gmb.jpeg?key=83439b8","postal":47809,"town":"Krefeld","keywords":"Dachdeckerei, Bedachungen, Bauklempnerei, Flachdach, Fassaden, Dachsanierung, Isolierungen, Wärmedämmung, Dachfenster, Dächer, Dachdecker, Dachdeckereien, Dachrinnenreinigung, Dachdeckermeister, Dachgaubenverkleidungen, Fassadendämmungen, Flachdachdämmungen, Sammelkästen, Solaranlagenmontage, Dachgeschossausbau, Flachdachbau, Dachreparaturservice, Flachdachabdichtung, Schieferdeckereien, Dämmung, Steildach, Dachrenovierung, Rinnen, Rinnenreparatur, Dachdämmungen, Dachfenstereinbau, Dachreinigung, Dacharbeiten, Dachbegrünung, Dachgauben, Dachrinnen, Holzbau, Klempnerarbeiten, Zimmerei, Zimmererarbeiten, Überdachungen, Dachdecker-Meisterbetrieb, Dachdecker Oppum, Veluxfenster","brands":"Marken:\nVeluxfenster","greview_1_rating":1,"greview_1_zeit":"vor einem Jahr","greview_1_text":"","greview_1_reviewer":"Lisa Brill","greview_1_localguide":1,"greview_1_beantwortet":""}}