{"hash":"878a597844db8e690a30b7fec33be346d7d73955","data":null,"context":{"id":"add5ec8a-3a4b-4462-9488-cf8b47fc3fa1","name":"Sängerheim","branch":"Gastronomie","phone":"02452 6 16 88","email":"info@saengerheim-dremmen.de","website":"http://www.gaestehaus-sarah.de","address":"Erkelenzer Str. 11","image":"","postal":52525,"town":"Heinsberg","keywords":"","brands":"","greview_1_rating":"","greview_1_zeit":"","greview_1_text":"","greview_1_reviewer":"","greview_1_localguide":"","greview_1_beantwortet":""}}