{"hash":"878a597844db8e690a30b7fec33be346d7d73955","data":null,"context":{"id":"b26c6eed-bf68-40cd-9b50-5ddef6049f5e","name":"Gaststätte Apfelbaum","branch":"Gastronomie >  Deutsch > Gastronomie","phone":"0201 45 04 44 00","email":"allesknackig.allesfrisch@apfel-baum-werden.de","website":"http://www.apfel-baum-werden.de","address":"Viehauser Berg 17","image":"","postal":45239,"town":"Essen","keywords":"Gaststätte","brands":"","greview_1_rating":1,"greview_1_zeit":"vor einem Jahr","greview_1_text":"","greview_1_reviewer":"Tr1stan _07","greview_1_localguide":0,"greview_1_beantwortet":""}}