{"hash":"878a597844db8e690a30b7fec33be346d7d73955","data":null,"context":{"id":"6b5909c9-0aba-4a21-8741-9fdfeaa481b2","name":"Pizzeria Rigatoni Inh. Aladdin Ademi","branch":"Gastronomie","phone":"0208 62 01 82 40","email":"rigatonilebensmittel@hotmail.de","website":"http://www.pizzeriarigatoni.de","address":"Mülheimer Str. 325","image":"","postal":46045,"town":"Oberhausen","keywords":"Service, Pizzeria, Lieferservice","brands":"","greview_1_rating":1,"greview_1_zeit":"vor 2 Wochen","greview_1_text":"Kann man absolut vergessen, die schlechteste Pizzeria die es gibt. Teig ist roh und ungenießbar. Am Telefon wird gesagt man soll wo anders bestellen. Nie wieder! Die Bewertungen sprechen für sich. Schrottladen!!!","greview_1_reviewer":"Sven Schulze","greview_1_localguide":0,"greview_1_beantwortet":""}}