{"hash":"878a597844db8e690a30b7fec33be346d7d73955","data":null,"context":{"id":"444d3f4c-12ec-47ac-bf36-86b7d2423c1d","name":"Gasstätte Venner","branch":"Gastronomie","phone":"02161 5 17 11","email":"hamerhoefgen@t-online.de","website":"http://www.hamerhoefgen.de","address":"Höfgenweg 19","image":"","postal":41068,"town":"Mönchengladbach","keywords":"","brands":"","greview_1_rating":1,"greview_1_zeit":"vor 6 Monaten","greview_1_text":"Garnelen  waren Krabben  in der Tonpfanne,  insgesamt waren wir nicht zufrieden, der neue Kellner, der offensichtlich nicht gut eingearbeitet wurde, war überfordert, da konnte er aber nichts für, der Wirt hätte ihn besser  instruieren müssen und selber reagieren müssen , insgesamt haben wir Geburtstag gefeiert und es war nicht schön und nicht gut, einzig das Essen war teils gut, der Schafskäse und der fisch und die Pommes, der Rest gruselig. Die Getränke über der Bekleidung wurden vom Wirt auch nicht entschuldigt...","greview_1_reviewer":"Charlotte Morick","greview_1_localguide":0,"greview_1_beantwortet":""}}