{"hash":"878a597844db8e690a30b7fec33be346d7d73955","data":null,"context":{"id":"e968bd7c-014e-4ad8-ba21-4bd1a337ad8b","name":"Appelt","branch":"Tischlereien","phone":"0203 2 38 16","email":"jensappelt@gmx.de","website":"http://www.schreinerei-appelt.de/","address":"Düsseldorfer Str. 100","image":"","postal":47051,"town":"Duisburg","keywords":"Fenster, Möbel, Parkett, Treppen, Türen, Meisterbetrieb, Schreinerei, Innenausbau, Appelt, Jens Appelt","brands":"Marken:\nAppelt\nJens Appelt","greview_1_rating":1,"greview_1_zeit":"vor 11 Monaten","greview_1_text":"Mir wurde ein Ausbildungsplatz zugesprochen und dann meine Bewerbung eingereicht habe. 3 Monate später wurde an jemand weiter gegeben. Jens Appelt ist nicht gut. Gisbert Applet war ein super Chef wo man was lernen konnte.","greview_1_reviewer":"Shanxi TV","greview_1_localguide":0,"greview_1_beantwortet":""}}