{"hash":"878a597844db8e690a30b7fec33be346d7d73955","data":null,"context":{"id":"b0b613bb-d681-491f-8ab5-83fe24628c5e","name":"Winterscheidt","branch":"Medizin >  Lasertherapie > Allergologie > Haut- und Geschlechtskrankheiten","phone":"02162 95 22 22","email":"mw@derma-viersen.de","website":"https://www.derma-viersen.de","address":"Moselstr. 23","image":"","postal":41751,"town":"Viersen","keywords":"Lasermedizin, Feuermal, Blutschwamm, Alterswarzen, Fibrome, Warzen, Stielwarzen, Xanthelasmen, Altersflecken, Besereisser, Besenreisser, Laser, Radiesse, Hyaluronsäure, Botox, Anti-Aging, Hautkrebsfrüherkennung, Dermatologie, Onkologie, Sonnenallergie, Berufskrankheit, Vorsorge, Kosmetologie, Aknebehandlung, Allergiebehandlungen, Hautanalyse, Hautbehandlung, Ambulante Hautoperationen, Hautpilztherapie, Nagelpilz, Puva-Therapie, Schwarzer Hautkrebs, Weißer Hautkrebs, Narbenbehandlung, Allergologie, dermat. Laser, Hautarzt, Hautärztin, Laserbehandlung, Phlebologie, Allergietest, Ekzem, Heuschnupfen, Nahrungsmittelallergie, Pollen, Psychosomatik, Sonnenschutz, Venenerkrankungen","brands":"","greview_1_rating":1,"greview_1_zeit":"vor 2 Monaten","greview_1_text":"Wenn es um wichtige Dinge geht, wie zum Beispiel die Zukunft im Beruf. Absolut nicht empfehlenswert. Sätze zu hören bekommen, wie: „ dann sind sie eben arbeitslos“ oder „in 2-3 Tagen ist alles weg“.Nach gut mehr als einem Jahr immer noch das selbe Problem.Nun beim anderen Hautarzt Termin bekommen der sofort die Berufsgenossenschaft einschaltete, das Problem richtig erkannt hat.Nur ist es für die BG jetzt zu spät, weil ab dem 1.8. ich meinen Beruf nicht mehr ausüben werde bzw kann, und auch bis dahin freigestellt wurde. Also wenn es wirklich dringend und schlimm ist , wartet lieber auf einen Termin.","greview_1_reviewer":"Paddy","greview_1_localguide":0,"greview_1_beantwortet":""}}