{"hash":"65e2bbd09f8cf90eca8adbf53c9f9312bd816ae9","data":null,"context":{"id":"c008dc6d-723f-4f9d-b2bc-897785dffba3","name":"Wacker Thomas u. Keulen Margarete Dr.med.","branch":"Medizin >  Hals-Nasen-Ohrenheilkunde > Allergologie","phone":"02166 4 60 44","email":"info@wacker-hno.de","website":"http://www.wacker-hno.de","address":"Stresemannstr. 44","image":"","postal":41236,"town":"Mönchengladbach","keywords":"Allergie, Allergiebehandlung, Allergieberatung, Allergieberatungen, Allergiediagnostik, Allergie Diagnostik, Allergietest, Allergietests, Allergologen, Allergologie, Ambulante Operationen, Balance Board, Blutdiagnostik, Celontherapie, Digitale Radiologie, Dr.med., DVT, Fachärztin, Fliegerärztliche Untersuchungsstelle, Gutachterfähigkeit, Hals Nasen Ohren, Hals-Nasen-Ohrenarzt, Hals-Nasen-Ohren-Arzt, Hals-Nasen-Ohrenheilkunde, HNO, HNO-Arzt, HNO-Heilkunde, Hörgeräte, Impfung, Innere Medizin, Internist, Intoleranz, Keulen Margarete, Krebsvorsorge im HNO-Bereich, Naturheilverfahren, Neugeborenen-Hörscreening, Pädaugiologie, Pädautiologie, Phoniatrie, Pneumologe, Pneumologie, Radiofrequenzchirurgie, Radiologie HNO, Scharnchoperationen, Schlaf-Apnoe-Screening, Schlafmedizin, Schnarchoperationen, Schwindeldiagnostik, Schwindelpatienten, Sprachstörungen, Stimmstörungen, Stimm- u. Sprachstörungen, Teilradiologie, Tinitusdiagnostik, Tinitusretraining, Tinitustherapie, Tinnitus, Tinnitustherapie, Tinnitustraining, Ultraschall, Umweltmedizin, Verkehrsmedizin, Verkehrsmedizinische Begutachtung, Wahrnehmungsstörungen, Allergien, Asthma, Celon-Methode, DVT Röntgenverfahren, Fliegerärztliche Untersuchungsstelle HNO, Gutachtertätigkeit, Hausstaub, Heuschnupfen, Hörbehinderung, Hördiagnostik bei Kindern und Erwachsenen (BERA), Hördiagnostik bei Neugeborenen (OAE), Hörscreening, Hörsturz, Lungenfunktionsmessung, Minimalinvasiven Eingriffe, Nahrungsmittelunverträglichkeit, Neurootologie (BV HNO), Pädaudiologie, Radiologie (HNO), Rhinomanometrie, Röntgen, Röntgendiagnostik, Sauerstofftherapie, Schnarchen, Schnarchtherapie, Schwindel, Schwindeltherapie, Tauchtauglichkeitstest, Tumornachsorge, Ultraschalluntersuchungen (A- und B-Scan), Verkehrsmedizinische Begutachtung Vorsorgeuntersuchungen, auditiven Wahrnehmungsstörungen, digitale Volumentomografie, kindliche Hörstörung, DVT-Röntgentechnik, Hörgerätekontrolle, Krebsvorsoge im HNO Bereich, Radiologie, Stimm- und Sprachförderung, Tinnitus-Therapie, Tinnitusanalyse, Ultraschalldiagnostik, auditive Wahrnehmungsstörungen, Tinnitusdiagnostik, Tinnitusretraining, HNO-Arztpraxen, Hno-Ärzte, Hörsturztherapie","brands":"","greview_1_rating":1,"greview_1_zeit":"vor 6 Monaten","greview_1_text":"Einmal war ich beim diesen Arzt. Der Arzt ist ganz gut. Aber er hat eine Angestellte, die beim Arzt arbeit. Sie ist große Junge  Frau als andere. Ich weiß nicht ihr Name. Leider soll ich Mich feststellen, dass sie kein Ausländer mag. 2 mal habe ich sie gesehen, dass sie die Papiere der Ausländer, die zum Test dran waren, abgelegt und die Deutschen Aufgerufen hat.  Es ist echt Rasismus. Es ist Katastrophe aber nicht nur für uns sondern auch für diesen Arzt.","greview_1_reviewer":"Kried Carry","greview_1_localguide":0,"greview_1_beantwortet":""}}