{"hash":"878a597844db8e690a30b7fec33be346d7d73955","data":null,"context":{"id":"58496299-63f9-4042-a793-84c7b7232f3f","name":"Terra-Dächer","branch":"Terrassenüberdachungen","phone":"0221 79 10 55 56","email":"info@terra-daecher.de","website":"http://www.terra-daecher.de","address":"Robert-Bosch-Str. 37","image":"","postal":50769,"town":"Köln","keywords":"Carports, Dachbeschichtung, Dachlackierung, Dachreinigung, Dachsanierung, Dachziegel, Eingangsüberwachung, Fassadenschutz, Fliegenschutz, Frostschutz, Garagentore, Gartenhäuser, Getöntes Dachglas, Hofüberdachung, Insektenschutz, LED, Lichtschachtabdeckung, Markisen, Moskitoschutz, Poolüberdachungen, Regenschutz, Rollos, Schiebeanlagen, Terrassendächer, Terrassenüberdachungen, Torantriebe, Unterstand, Vordächer, Windfang, Wintergarten, Wintergartenbeleuchtung, Wohnraumerweiterung, Zweiradgarage, Überdachung","brands":"","greview_1_rating":"","greview_1_zeit":"","greview_1_text":"","greview_1_reviewer":"","greview_1_localguide":"","greview_1_beantwortet":""}}